tux/__init__.py
tux/checkpoint.py
tux/config.py
tux/distributed.py
tux/jax_utils.py
tux/loss.py
tux/misc.py
tux/optimizers.py
tux/stats.py
tux/utils.py
tux/wandb.py
tux-0.0.2.dist-info/METADATA
tux-0.0.2.dist-info/WHEEL
tux-0.0.2.dist-info/top_level.txt
tux-0.0.2.dist-info/RECORD
